README.md
setup.cfg
setup.py
op.py.egg-info/PKG-INFO
op.py.egg-info/SOURCES.txt
op.py.egg-info/dependency_links.txt
op.py.egg-info/requires.txt
op.py.egg-info/top_level.txt
oppy/__init__.py
oppy/client.py
oppy/http.py
oppy/map.py
oppy/mapstats.py
oppy/token.py
oppy/user.py
oppy/userstats.py