Metadata-Version: 2.1
Name: op.py
Version: 1.0.0
Summary: A wrapper made for the osu! v2 API.
Home-page: https://github.com/waydealphax/oppy
Author: Wayde B
Author-email: wayde@alphaxdev.xyz
License: MIT
Keywords: osuapi,osu,osuapiv2
Platform: UNKNOWN
Classifier: Development Status :: 5 - Production/Stable
Classifier: Programming Language :: Python :: 3
Classifier: Programming Language :: Python :: 3.9
